[{"mission":"ISS009","roll":"E","frame":"5089","w":"1200","h":"816","size":"249418","cldp":"10","lat":"20.5","lon":"-103.5","geon":"MEXICO","feat":"GUADALAJARA LAKE CHAPALA SUNGLINT","url":"http:\/\/eol.jsc.nasa.gov\/sseop\/images\/city\/lowres\/ISS009\/ISS009-E-5089.JPG"},{"mission":"ISS009","roll":"E","frame":"5090","w":"540","h":"357","size":"57781","cldp":"10","lat":"20.5","lon":"-103.0","geon":"MEXICO","feat":"LAKE CHAPALA SUNGLINT GUADALAJARA","url":"http:\/\/eol.jsc.nasa.gov\/sseop\/images\/EFS\/lowres\/ISS009\/ISS009-E-5090.JPG"},{"mission":"ISS009","roll":"E","frame":"5696","w":"540","h":"357","size":"196179","cldp":"25","lat":"-16.0","lon":"-68.5","geon":"BOLIVIA","feat":"LAKE TITICACA PLANKTON BLOOM","url":"http:\/\/eol.jsc.nasa.gov\/sseop\/images\/EFS\/lowres\/ISS009\/ISS009-E-5696.JPG"},{"mission":"ISS009","roll":"E","frame":"5944","w":"538","h":"268","size":"41899","cldp":"10","lat":"31.9","lon":"-113.4","geon":"MEXICO","feat":"VOLCANIC CONES LAVA DRAINAGE","url":"http:\/\/eol.jsc.nasa.gov\/sseop\/images\/EFS\/lowres\/ISS009\/ISS009-E-5944.JPG"},{"mission":"ISS009","roll":"E","frame":"5953","w":"538","h":"538","size":"72911","cldp":"10","lat":"32.0","lon":"-113.5","geon":"MEXICO","feat":"PINACATE CINDER CONES DUNES ADAIR BAY","url":"http:\/\/eol.jsc.nasa.gov\/sseop\/images\/EFS\/lowres\/ISS009\/ISS009-E-5953.JPG"},{"mission":"ISS009","roll":"E","frame":"9839","w":"540","h":"357","size":"51566","cldp":"10","lat":"32.0","lon":"-115.0","geon":"MEXICO","feat":"COLORADO RIVER DELTA ALTAR DESERT","url":"http:\/\/eol.jsc.nasa.gov\/sseop\/images\/EFS\/lowres\/ISS009\/ISS009-E-9839.JPG"},{"mission":"ISS009","roll":"E","frame":"9952","w":"395","h":"262","size":"30366","cldp":"25","lat":"36.0","lon":"-5.5","geon":"SPAIN","feat":"SUNGLINT WAVES STRAIT OF GIBRALTAR","url":"http:\/\/eol.jsc.nasa.gov\/sseop\/images\/EFS\/lowres\/ISS009\/ISS009-E-9952.JPG"},{"mission":"ISS009","roll":"E","frame":"9954","w":"396","h":"253","size":"31722","cldp":"25","lat":"36.0","lon":"-5.0","geon":"SPAIN","feat":"SUNGLINT WAVES STRAIT OF GIBRALTAR","url":"http:\/\/eol.jsc.nasa.gov\/sseop\/images\/EFS\/lowres\/ISS009\/ISS009-E-9954.JPG"},{"mission":"ISS009","roll":"E","frame":"9985","w":"540","h":"540","size":"77994","cldp":"10","lat":"40.5","lon":"1.0","geon":"SPAIN","feat":"SUNGLINT WAVES EBRO RIVER DELTA","url":"http:\/\/eol.jsc.nasa.gov\/sseop\/images\/EFS\/lowres\/ISS009\/ISS009-E-9985.JPG"},{"mission":"ISS009","roll":"E","frame":"9987","w":"540","h":"405","size":"86460","cldp":"10","lat":"41.5","lon":"2.0","geon":"SPAIN","feat":"BARCELONA MOUNTAINS RIVER AIRPORT","url":"http:\/\/eol.jsc.nasa.gov\/sseop\/images\/EFS\/lowres\/ISS009\/ISS009-E-9987.JPG"},{"mission":"ISS009","roll":"E","frame":"9987","w":"1200","h":"816","size":"200225","cldp":"10","lat":"41.5","lon":"2.0","geon":"SPAIN","feat":"BARCELONA MOUNTAINS RIVER AIRPORT","url":"http:\/\/eol.jsc.nasa.gov\/sseop\/images\/city\/lowres\/ISS009\/ISS009-E-9987.JPG"},{"mission":"ISS009","roll":"E","frame":"10382","w":"540","h":"540","size":"104330","cldp":"10","lat":"32.0","lon":"-111.0","geon":"USA-ARIZONA","feat":"TUCSON SANTA CRUZ R. MTS.","url":"http:\/\/eol.jsc.nasa.gov\/sseop\/images\/EFS\/lowres\/ISS009\/ISS009-E-10382.JPG"},{"mission":"ISS009","roll":"E","frame":"11537","w":"540","h":"540","size":"125754","cldp":"10","lat":"38.0","lon":"23.7","geon":"GREECE","feat":"ATHENS HARBORS AIRPORTSMTS.","url":"http:\/\/eol.jsc.nasa.gov\/sseop\/images\/EFS\/lowres\/ISS009\/ISS009-E-11537.JPG"},{"mission":"ISS009","roll":"E","frame":"11646","w":"1200","h":"816","size":"319782","cldp":"10","lat":"41.5","lon":"69.5","geon":"UZBEKISTAN","feat":"TASHKENT AGRI.CHIRCHIK R. V.","url":"http:\/\/eol.jsc.nasa.gov\/sseop\/images\/city\/lowres\/ISS009\/ISS009-E-11646.JPG"},{"mission":"ISS009","roll":"E","frame":"11651","w":"1200","h":"816","size":"350194","cldp":"10","lat":"40.5","lon":"72.0","geon":"UZBEKISTAN","feat":"FERGANA MARGILAN AGRI. RES.","url":"http:\/\/eol.jsc.nasa.gov\/sseop\/images\/city\/lowres\/ISS009\/ISS009-E-11651.JPG"},{"mission":"ISS009","roll":"E","frame":"11739","w":"1200","h":"816","size":"211808","cldp":"10","lat":"40.5","lon":"50.0","geon":"AZERBAIJAN","feat":"BAKU HARBOR LAKES ROADS I.","url":"http:\/\/eol.jsc.nasa.gov\/sseop\/images\/city\/lowres\/ISS009\/ISS009-E-11739.JPG"},{"mission":"ISS009","roll":"E","frame":"12329","w":"540","h":"540","size":"86611","cldp":"10","lat":"19.7","lon":"-70.4","geon":"DOMINICAN REPUBLIC","feat":"SOSUA REEFS FOREST CABARETE BAY","url":"http:\/\/eol.jsc.nasa.gov\/sseop\/images\/EFS\/lowres\/ISS009\/ISS009-E-12329.JPG"},{"mission":"ISS009","roll":"E","frame":"12441","w":"540","h":"356","size":"305106","cldp":"10","lat":"25.6","lon":"28.7","geon":"EGYPT","feat":"GEBEL EDMONSTONE DUNES","url":"http:\/\/eol.jsc.nasa.gov\/sseop\/images\/EFS\/lowres\/ISS009\/ISS009-E-12441.JPG"},{"mission":"ISS009","roll":"E","frame":"13366","w":"540","h":"553","size":"87653","cldp":"25","lat":"-3.1","lon":"37.3","geon":"TANZANIA","feat":"MOUNT KILIMANJARO GLACIERS","url":"http:\/\/eol.jsc.nasa.gov\/sseop\/images\/EFS\/lowres\/ISS009\/ISS009-E-13366.JPG"},{"mission":"ISS009","roll":"E","frame":"13498","w":"1200","h":"816","size":"224155","cldp":"10","lat":"45.0","lon":"-93.0","geon":"USA-MINNESOTA","feat":"MINNEAPOLIS ST. PAUL AREA","url":"http:\/\/eol.jsc.nasa.gov\/sseop\/images\/city\/lowres\/ISS009\/ISS009-E-13498.JPG"},{"mission":"ISS009","roll":"E","frame":"13505","w":"1200","h":"816","size":"291800","cldp":"10","lat":"42.5","lon":"-90.5","geon":"USA-ILLINOIS","feat":"DUBUQUE MISSISSIPPI R. AGRI.","url":"http:\/\/eol.jsc.nasa.gov\/sseop\/images\/city\/lowres\/ISS009\/ISS009-E-13505.JPG"},{"mission":"ISS009","roll":"E","frame":"13507","w":"1200","h":"816","size":"221673","cldp":"10","lat":"42.5","lon":"-89.0","geon":"USA-WISCONSIN","feat":"BELOIT JANESVILLE ROCKFORD","url":"http:\/\/eol.jsc.nasa.gov\/sseop\/images\/city\/lowres\/ISS009\/ISS009-E-13507.JPG"},{"mission":"ISS009","roll":"E","frame":"13521","w":"816","h":"1200","size":"221961","cldp":"10","lat":"42.0","lon":"-88.0","geon":"USA-ILLINOIS","feat":"CHICAGO AIRPORTS L. MICHIGAN","url":"http:\/\/eol.jsc.nasa.gov\/sseop\/images\/city\/lowres\/ISS009\/ISS009-E-13521.JPG"},{"mission":"ISS009","roll":"E","frame":"13539","w":"1200","h":"816","size":"164788","cldp":"10","lat":"37.5","lon":"-80.0","geon":"USA-VIRGINIA","feat":"ROANOKE BLUE RIDGE MTS. FOR.","url":"http:\/\/eol.jsc.nasa.gov\/sseop\/images\/city\/lowres\/ISS009\/ISS009-E-13539.JPG"},{"mission":"ISS009","roll":"E","frame":"15488","w":"540","h":"312","size":"246891","cldp":"25","lat":"-3.0","lon":"-60.0","geon":"BRAZIL","feat":"MANAUS AMAZON NEGRO CONFLUEN","url":"http:\/\/eol.jsc.nasa.gov\/sseop\/images\/EFS\/lowres\/ISS009\/ISS009-E-15488.JPG"},{"mission":"ISS009","roll":"E","frame":"16836","w":"540","h":"540","size":"449542","cldp":"10","lat":"51.8","lon":"157.5","geon":"RUSSIAN FEDERATION","feat":"KSUDACH VOLCANO LAKE FOREST RAVINES","url":"http:\/\/eol.jsc.nasa.gov\/sseop\/images\/EFS\/lowres\/ISS009\/ISS009-E-16836.JPG"},{"mission":"ISS009","roll":"E","frame":"18679","w":"540","h":"727","size":"538807","cldp":"10","lat":"46.9","lon":"51.7","geon":"KAZAKHSTAN","feat":"URAL RIVER DELTA CANALS","url":"http:\/\/eol.jsc.nasa.gov\/sseop\/images\/EFS\/lowres\/ISS009\/ISS009-E-18679.JPG"},{"mission":"ISS009","roll":"E","frame":"19682","w":"540","h":"540","size":"75410","cldp":"10","lat":"10.0","lon":"-71.0","geon":"VENEZUELA","feat":"LAKE MARACAIBO GLINT PLATTERNS","url":"http:\/\/eol.jsc.nasa.gov\/sseop\/images\/EFS\/lowres\/ISS009\/ISS009-E-19682.JPG"},{"mission":"ISS009","roll":"E","frame":"20440","w":"540","h":"334","size":"35057","cldp":"50","lat":"15.0","lon":"-49.0","geon":"ATLANTIC OCEAN","feat":"PAN-HURRICANE FRANCES","url":"http:\/\/eol.jsc.nasa.gov\/sseop\/images\/EFS\/lowres\/ISS009\/ISS009-E-20440.JPG"},{"mission":"ISS009","roll":"E","frame":"22160","w":"540","h":"324","size":"94705","cldp":"100","lat":"18.2","lon":"-79.7","geon":"CARIBBEAN SEA","feat":"PAN-HURRICANE IVAN BANDS EYE","url":"http:\/\/eol.jsc.nasa.gov\/sseop\/images\/EFS\/lowres\/ISS009\/ISS009-E-22160.JPG"},{"mission":"ISS009","roll":"E","frame":"22625","w":"540","h":"451","size":"453029","cldp":"10","lat":"-34.0","lon":"-70.0","geon":"CHILE","feat":"VOLCAN MAIPO LAKE DIAMANTE","url":"http:\/\/eol.jsc.nasa.gov\/sseop\/images\/EFS\/lowres\/ISS009\/ISS009-E-22625.JPG"},{"mission":"ISS009","roll":"E","frame":"23808","w":"540","h":"357","size":"262208","cldp":"10","lat":"18.8","lon":"37.5","geon":"SUDAN","feat":"CORAL REEFS RED SEA","url":"http:\/\/eol.jsc.nasa.gov\/sseop\/images\/EFS\/lowres\/ISS009\/ISS009-E-23808.JPG"},{"mission":"ISS009","roll":"E","frame":"28346","w":"357","h":"540","size":"254541","cldp":"10","lat":"46.2","lon":"-122.2","geon":"USA-WASHINGTON","feat":"MT. ST. HELENS STEAM","url":"http:\/\/eol.jsc.nasa.gov\/sseop\/images\/EFS\/lowres\/ISS009\/ISS009-E-28346.JPG"}]